.gitignore
.gitmodules
.npmignore
.pre-commit-config.yaml
.vale.ini
CODE_OF_CONDUCT.md
LICENSE
MANIFEST.in
README.md
package-lock.json
package.json
pyproject.toml
ruff.toml
setup.py
.github/pull_request_template.md
.github/ISSUE_TEMPLATE/bug_report.md
.github/ISSUE_TEMPLATE/feature_request.md
.github/workflows/manual_test-pypi.yml
.github/workflows/publish_docs.yml
.github/workflows/release.yml
.github/workflows/test.yml
TheengsGateway/__init__.py
TheengsGateway/__main__.py
TheengsGateway/ble_gateway.py
TheengsGateway/config.py
TheengsGateway/decryption.py
TheengsGateway/diagnose.py
TheengsGateway/discovery.py
TheengsGateway/privacy.py
bin/TheengsGateway
docs/README.md
docs/.vuepress/config.js
docs/.vuepress/public/apple-touch-icon.png
docs/.vuepress/public/favicon-144x144.png
docs/.vuepress/public/favicon-16x16.png
docs/.vuepress/public/favicon-32x32.png
docs/.vuepress/styles/index.styl
docs/img/Theengs-IRK-extraction.png
docs/img/TheengsGateway_controllers.png
docs/img/TheengsGateway_mqtt_explorer.png
docs/img/Victron01.png
docs/img/Victron02.png
docs/img/logo-Theengs.png
docs/install/install.md
docs/participate/adding-decoders.md
docs/participate/development.md
docs/participate/support.md
docs/prerequisites/broker.md
docs/prerequisites/controller.md
docs/prerequisites/hardware.md
docs/use/use.md
theengsgateway.egg-info/PKG-INFO
theengsgateway.egg-info/SOURCES.txt
theengsgateway.egg-info/dependency_links.txt
theengsgateway.egg-info/requires.txt
theengsgateway.egg-info/top_level.txt
vale/styles/config/vocabularies/Theengs/accept.txt