Metadata-Version: 2.4
Name: theengsgateway
Version: 1.6.0
Home-page: https://github.com/theengs/gateway
Author: Theengs
License: GPL-3.0 License
License-File: LICENSE
Requires-Dist: bleak>=0.19.0
Requires-Dist: bluetooth-adapters>=0.15.3; python_version >= "3.9"
Requires-Dist: bluetooth-clocks<1.0
Requires-Dist: bluetooth-numbers<2.0,>=1.0
Requires-Dist: importlib-metadata
Requires-Dist: paho-mqtt<3.0.0,>=2.0.0
Requires-Dist: pycryptodomex>=3.18.0
Requires-Dist: theengsdecoder>=1.9.5
Dynamic: author
Dynamic: description
Dynamic: description-content-type
Dynamic: home-page
Dynamic: license
Dynamic: license-file
Dynamic: requires-dist
